exceltomysql/__init__.py
exceltomysql/_api.py
exceltomysql/exceltomysql.py
exceltomysql-0.2.3.dist-info/LICENSE
exceltomysql-0.2.3.dist-info/METADATA
exceltomysql-0.2.3.dist-info/WHEEL
exceltomysql-0.2.3.dist-info/top_level.txt
exceltomysql-0.2.3.dist-info/RECORD
