Metadata-Version: 2.1
Name: exceltomysql
Version: 0.2.3
Summary: This package help convert your excel files (xlsx,xls,csv) to MySQL Database.
Home-page: https://github.com/Xiangyongluo/exceltomysql
Author: Xiangyong Luo
Author-email: rochemay@163.com
Classifier: Programming Language :: Python :: 3
Classifier: License :: OSI Approved :: MIT License
Classifier: Operating System :: OS Independent
Requires-Python: >=3.10
License-File: LICENSE
Requires-Dist: pandas
Requires-Dist: pymysql
Requires-Dist: sqlalchemy
Requires-Dist: pyufunc
